timestamper99/__init__.py
timestamper99/test.py
timestamper99-0.0.2.dist-info/LICENSE
timestamper99-0.0.2.dist-info/METADATA
timestamper99-0.0.2.dist-info/WHEEL
timestamper99-0.0.2.dist-info/top_level.txt
timestamper99-0.0.2.dist-info/RECORD
