Metadata-Version: 2.1
Name: timestamper99
Version: 0.0.2
Summary: A package to print time stamp
Author: Sandun Sampath Vitharana (ssv)
Author-email: <vitharana1996@gmail.com>
Keywords: python,time
Classifier: Development Status :: 1 - Planning
Classifier: Intended Audience :: Developers
Classifier: Programming Language :: Python :: 3
Classifier: Operating System :: Unix
Classifier: Operating System :: MacOS :: MacOS X
Classifier: Operating System :: Microsoft :: Windows
License-File: LICENSE
Requires-Dist: pyserial
